{
  "db_name": "PostgreSQL",
  "query": "SELECT providers.*, count(sources.id)::INT as \"num_sources!\" FROM providers LEFT JOIN sources ON providers.id = sources.provider_id GROUP BY providers.id ORDER BY providers.enabled DESC, providers.name",
  "describe": {
    "columns": [
      {
        "ordinal": 0,
        "name": "id",
        "type_info": "Text"
      },
      {
        "ordinal": 1,
        "name": "created_at",
        "type_info": "Timestamp"
      },
      {
        "ordinal": 2,
        "name": "updated_at",
        "type_info": "Timestamp"
      },
      {
        "ordinal": 3,
        "name": "name",
        "type_info": "Text"
      },
      {
        "ordinal": 4,
        "name": "description",
        "type_info": "Text"
      },
      {
        "ordinal": 5,
        "name": "url",
        "type_info": "Text"
      },
      {
        "ordinal": 6,
        "name": "favicon",
        "type_info": "Text"
      },
      {
        "ordinal": 7,
        "name": "tags",
        "type_info": "TextArray"
      },
      {
        "ordinal": 8,
        "name": "enabled",
        "type_info": "Bool"
      },
      {
        "ordinal": 9,
        "name": "num_sources!",
        "type_info": "Int4"
      }
    ],
    "parameters": {
      "Left": []
    },
    "nullable": [
      false,
      false,
      false,
      false,
      false,
      false,
      true,
      false,
      false,
      null
    ]
  },
  "hash": "c26f4f043b411cb7e98bfea7b4253d411d54e47ebf299f8410bb22b0db08ed54"
}
